<?xml version="1.0" encoding="UTF-8"?>
<MetaDataObject xmlns="http://v8.1c.ru/8.3/MDClasses" xmlns:app="http://v8.1c.ru/8.2/managed-application/core" xmlns:cfg="http://v8.1c.ru/8.1/data/enterprise/current-config" xmlns:cmi="http://v8.1c.ru/8.2/managed-application/cmi" xmlns:ent="http://v8.1c.ru/8.1/data/enterprise" xmlns:lf="http://v8.1c.ru/8.2/managed-application/logform" xmlns:style="http://v8.1c.ru/8.1/data/ui/style" xmlns:sys="http://v8.1c.ru/8.1/data/ui/fonts/system" xmlns:v8="http://v8.1c.ru/8.1/data/core" xmlns:v8ui="http://v8.1c.ru/8.1/data/ui" xmlns:web="http://v8.1c.ru/8.1/data/ui/colors/web" xmlns:win="http://v8.1c.ru/8.1/data/ui/colors/windows" xmlns:xen="http://v8.1c.ru/8.3/xcf/enums" xmlns:xpr="http://v8.1c.ru/8.3/xcf/predef" xmlns:xr="http://v8.1c.ru/8.3/xcf/readable" xmlns:xs="http://www.w3.org/2001/XMLSchema" xmlns:xsi="http://www.w3.org/2001/XMLSchema-instance" version="2.7">
	<Constant uuid="7c9cc7c4-cae2-409b-b754-0950e5309e50">
		<InternalInfo>
			<xr:GeneratedType name="ConstantManager.нсиНастройкаЦветовВизуализации" category="Manager">
				<xr:TypeId>5e4bae39-4500-43d5-8200-b1bbf50abbc0</xr:TypeId>
				<xr:ValueId>3212568e-000a-48ab-b735-ad721330594f</xr:ValueId>
			</xr:GeneratedType>
			<xr:GeneratedType name="ConstantValueManager.нсиНастройкаЦветовВизуализации" category="ValueManager">
				<xr:TypeId>1da95dde-b0c1-4aa9-a050-d189106fc0d3</xr:TypeId>
				<xr:ValueId>13641de3-5356-4781-959e-b7ee69544b1e</xr:ValueId>
			</xr:GeneratedType>
			<xr:GeneratedType name="ConstantValueKey.нсиНастройкаЦветовВизуализации" category="ValueKey">
				<xr:TypeId>e4435bd2-ae17-5adf-afd8-45e894a963d9</xr:TypeId>
				<xr:ValueId>58628972-b903-57ba-b6ba-fa9967e04101</xr:ValueId>
			</xr:GeneratedType>
		</InternalInfo>
		<Properties>
			<Name>нсиНастройкаЦветовВизуализации</Name>
			<Synonym>
				<v8:item>
					<v8:lang>ru</v8:lang>
					<v8:content>Цвет кириллических символов</v8:content>
				</v8:item>
			</Synonym>
			<Comment/>
			<Type>
				<v8:Type>v8:ValueStorage</v8:Type>
			</Type>
			<UseStandardCommands>true</UseStandardCommands>
			<DefaultForm>CommonForm.нсиНастройкаПараметровУчета</DefaultForm>
			<ExtendedPresentation/>
			<Explanation/>
			<PasswordMode>false</PasswordMode>
			<Format/>
			<EditFormat/>
			<ToolTip/>
			<MarkNegatives>false</MarkNegatives>
			<Mask/>
			<MultiLine>false</MultiLine>
			<ExtendedEdit>false</ExtendedEdit>
			<MinValue xsi:nil="true"/>
			<MaxValue xsi:nil="true"/>
			<FillChecking>DontCheck</FillChecking>
			<ChoiceFoldersAndItems>Items</ChoiceFoldersAndItems>
			<ChoiceParameterLinks/>
			<ChoiceParameters/>
			<QuickChoice>Auto</QuickChoice>
			<ChoiceForm/>
			<LinkByType/>
			<ChoiceHistoryOnInput>Auto</ChoiceHistoryOnInput>
			<DataLockControlMode>Managed</DataLockControlMode>
			<DataHistory>DontUse</DataHistory>
		</Properties>
	</Constant>
</MetaDataObject>